Workbook
Name AMBER_BUFFER: SETTINGS!$B$5
Name FX_RATES_TABLE: SETTINGS!$A$38:$C$40
Name FUND_MASTER_TABLE: SETTINGS!$A$17:$K$27

Sheet HOME
A1: ApolloCAM
A2: Daily Cash Management · Apollo Aligned Alternatives · Mumbai Fund Controllership
A3: As-of: 2026-06-01 · 11 Funds · ~$15.9B AUM · Controller: A. Shinde
A5: RED Funds | C5: AMBER Funds | E5: GREEN Funds | G5: BLUE (Excess)
A6: 3 | C6: 2 | E6: 4 | G6: 2
A9: DAILY WORKFLOW — Navigate using the sheet tabs below
A10: STEP 1 | C10: Import Positions | E10: _DATA sheet | G10: Paste daily JPM file into _DATA rows 4-50, or use VBA Load Data button
A11: STEP 2 | C11: Review Status | E11: DASHBOARD | G11: Verify RED/AMBER counts, check balances vs floors, review KPIs
A12: STEP 3 | C12: Approve Proposals | E12: PROPOSALS | G12: Review wire + FX proposals; change Action from PENDING → APPROVE/SKIP/HOLD
A13: STEP 4 | C13: Export Loaders | E13: LOADERS | G13: Locked after approval — export IVP XLSX, Trade CSV, SpotFX XLSX via VBA
A14: STEP 5 | C14: Submit & Confirm | E14: LOADERS | G14: Upload IVP file; enter confirmation references when bank confirms wires
A15: STEP 6 | C15: Archive | E15: VBA: Archive | G15: VBA ArchiveCurrentData() saves timestamped copy to Archive/ folder
A18: STATUS MODEL REFERENCE
A19: Status | B19: Condition | C19: Formula Zone | F19: Condition | H19: Notes
A20: RED | B20: Cash < Floor | F20: Immediate wire required. Source fund triggered.
A21: AMBER | B21: Floor ≤ Cash < Floor × 1.10 | F21: Watch closely. No wire required today.
A22: GREEN | B22: Floor × 1.10 ≤ Cash ≤ Ceiling | F22: Healthy operating range. No action needed.
A23: BLUE | B23: Cash > Ceiling | F23: Excess cash. Review for upward sweep or investment.
A26: VBA MACRO SETUP (optional — for automation buttons)
A27: 1. Save this file as ApolloCAM.xlsm (Excel Macro-Enabled Workbook)
A28: 2. Press Alt+F11 to open the VBA editor
A29: 3. File → Import File → select modApolloCAM.bas (from the vba/ folder)
A30: 4. Save again as .xlsm — macro ribbon buttons become active
A31: 5. Admin password to unlock Loaders: ApolloAdmin2026

Sheet DASHBOARD
A1: APOLLOCAM · DAILY CASH DASHBOARD · As-of: 2026-06-01
A3: RED Funds | C3: AMBER Funds | E3: GREEN Funds | G3: BLUE (Excess) | I3: Total Cash | K3: Batch
A4: 3 | C4: 2 | E4: 4 | G4: 2 | I4: 15858663 | K4: B20260601-001
A5: Formula: Status = IF(Cash<Floor,"RED", IF(Cash<Floor×AMBER_BUFFER,"AMBER", IF(Cash≤Ceiling,"GREEN","BLUE"))) · AMBER_BUFFER=1.10 · Cash = SUMIF(_DATA!FundCode, _DATA!FunctionalUSD)
A6: Fund Code | B6: Fund Name | C6: Type | D6: CCY | E6: Cash (USD) | F6: Floor | G6: Ceiling | H6: Status | I6: Surplus / (Deficit) | J6: Deficit | K6: % of Floor | L6: Routing Source
A7: AAA-AGG | B7: Apollo Aligned Alternatives Aggregator, L.P. | C7: Aggregator | D7: USD | E7: 2192987 | F7: 1500000 | G7: 3000000 | H7: GREEN | I7: 692987 | J7: 0 | K7: 146.19913
A8: AAA-LUX-AGG | B8: AAA Lux Aggregator, L.P. | C8: Aggregator | D8: USD | E8: 763759 | F8: 500000 | G8: 1000000 | H8: GREEN | I8: 263759 | J8: 0 | K8: 152.7518
A9: AAA-IDF-AGG | B9: AAA IDF, L.P. | C9: Aggregator | D9: USD | E9: 89635 | F9: 150000 | G9: 400000 | H9: RED | I9: -60365 | J9: 60365 | K9: 59.756667 | L9: AAA-AGG
A10: AAA-SF1Y | B10: AAA Sub Fund 1-Y, L.P. | C10: Sub-Fund | D10: USD | E10: 9281309 | F10: 2000000 | G10: 5000000 | H10: BLUE | I10: 7281309 | J10: 0 | K10: 464.06545 | L10: AAA-AGG
A11: AAA-MACS-Z | B11: AAA Multi-Asset Credit Strategies (Z), L.P. | C11: Sub-Fund | D11: USD | E11: 579030 | F11: 250000 | G11: 650000 | H11: GREEN | I11: 329030 | J11: 0 | K11: 231.612 | L11: AAA-AGG
A12: AAA-DL-Y | B12: AAA Direct Lending (Y), L.P. | C12: Sub-Fund | D12: USD | E12: -77734 | F12: 100000 | G12: 300000 | H12: RED | I12: -177734 | J12: 177734 | K12: -77.734 | L12: AAA-SF1Y
A13: AAA-HOSTPLUS-II | B13: Apollo HostPlus Credit II Holdings II, L.P. | C13: Sub-Fund | D13: USD | E13: 578460 | F13: 400000 | G13: 600000 | H13: GREEN | I13: 178460 | J13: 0 | K13: 144.615 | L13: AAA-AGG
A14: AAA-SF4Z | B14: AAA Sub Fund 4-Z, L.P. | C14: Sub-Fund | D14: USD | E14: 121002 | F14: 115000 | G14: 250000 | H14: AMBER | I14: 6002 | J14: 0 | K14: 105.21913 | L14: AAA-AGG
A15: AAA-SF2Y | B15: AAA Sub Fund 2-Y, L.P. | C15: Sub-Fund | D15: USD | E15: 114913 | F15: 110000 | G15: 300000 | H15: AMBER | I15: 4913 | J15: 0 | K15: 104.46636 | L15: AAA-AGG
A16: AAA-SF1YS | B16: AAA Sub Fund 1-YS, L.P. | C16: Sub-Fund | D16: USD | E16: 53101 | F16: 75000 | G16: 200000 | H16: RED | I16: -21899 | J16: 21899 | K16: 70.801333 | L16: AAA-SF1Y
A17: AAA-LIBRA | B17: Apollo Libra Credit Opportunities Fund, L.P. | C17: Sub-Fund | D17: USD | E17: 131363 | F17: 50000 | G17: 120000 | H17: BLUE | I17: 81363 | J17: 0 | K17: 262.726 | L17: AAA-AGG
A18: TOTAL | E18: 13827825

Sheet PROPOSALS
A1: APOLLOCAM · PROPOSALS — Wire Transfers & Spot FX Conversions · Batch: B20260601-001 | 2026-06-01
A3: WIRE TRANSFER PROPOSALS
A4: Formula: Wire Amount = MIN(Deficit, MAX(0, Source Balance − Source Floor − Prior Committed)) · Sorted by deficit descending · Sequential balance depletion prevents source over-commitment
A5: # | B5: From (Source) | C5: Source Name | D5: Source Balance | E5: Source Floor | F5: Prior Committed | G5: Source Available | H5: To (Deficit Fund) | I5: Deficit | J5: Wire Amount | K5: Post-Wire Balance | L5: Action | M5: Batch Reference
A6: 1 | B6: AAA-SF1Y | C6: AAA Sub Fund 1-Y, L.P. | D6: 9281309 | E6: 2000000 | F6: 0 | G6: 7281309 | H6: AAA-DL-Y | I6: 177734 | J6: 177734 | K6: 100000 | L6: APPROVE | M6: B20260601-001-W01
A7: 2 | B7: AAA-AGG | C7: Apollo Aligned Alternatives Aggregator, L.P. | D7: 2192987 | E7: 1500000 | F7: 0 | G7: 692987 | H7: AAA-IDF-AGG | I7: 60365 | J7: 60365 | K7: 150000 | L7: APPROVE | M7: B20260601-001-W02
A8: 3 | B8: AAA-SF1Y | C8: AAA Sub Fund 1-Y, L.P. | D8: 9281309 | E8: 2000000 | F8: 177734 | G8: 7103575 | H8: AAA-SF1YS | I8: 21899 | J8: 21899 | K8: 75000 | L8: APPROVE | M8: B20260601-001-W03
A9: TOTAL | J9: 325000
A12: SPOT FX CONVERSION PROPOSALS
A13: Formula: Sell Amount = Local Balance − Min Hold · USD Equivalent = Sell Amount × FX Rate · Value Date = WORKDAY(Run Date, SPOT_VALUE_LAG_DAYS=2, Holidays)
A14: # | B14: Fund Code | C14: Fund Name | D14: Sell CCY | E14: Local Balance | F14: Min Hold | G14: Sell Amount | H14: FX Rate | I14: USD Equivalent | J14: Value Date | K14: Counterparty | L14: Action | M14: Reference
A15: 1 | B15: AAA-LUX-AGG | C15: AAA Lux Aggregator, L.P. | D15: EUR | E15: 120000 | F15: 50000 | G15: 70000 | H15: 1.09 | I15: 76300 | J15: 2026-06-03 | K15: JP MORGAN FX | L15: APPROVE | M15: B20260601-001-FX01
A16: 2 | B16: AAA-MACS-Z | C16: AAA Multi-Asset Credit Strategies (Z), L.P. | D16: EUR | E16: 340000 | F16: 100000 | G16: 240000 | H16: 1.09 | I16: 261600 | J16: 2026-06-03 | K16: JP MORGAN FX | L16: APPROVE | M16: B20260601-001-FX02
A17: 3 | B17: AAA-HOSTPLUS-II | C17: Apollo HostPlus Credit II Holdings II, L.P. | D17: GBP | E17: 150000 | F17: 50000 | G17: 100000 | H17: 1.27 | I17: 127000 | J17: 2026-06-03 | K17: JP MORGAN FX | L17: APPROVE | M17: B20260601-001-FX03

Sheet LOADERS
A1: APOLLOCAM · LOADERS — IVP Wire / Trade Booking / Spot FX
A2: ⚠ This sheet is LOCKED after loader generation. Admin password required to unlock. All values are static — no formulas in output rows (EY requirement). Batch: B20260601-001 | Generated: 2026-06-01 08:42 UTC
A4: IVP WIRE LOADER — XLSX Export (3 wires)
A5: Sender Account | B5: Sender Bank | C5: Sender BIC | D5: Sender Entity | E5: Receiver Account | F5: Receiver Bank | G5: Receiver BIC | H5: Receiver Entity | I5: Amount (USD) | J5: CCY | K5: Value Date | L5: Reference | M5: Narrative | N5: Batch ID
A6: S 19834 | B6: JPMORGAN CHASE NA | C6: CHASUS33 | D6: AAA SUB FUND 1-Y LP INV ACC FBO WFG | E6: S 20986 | F6: JPMORGAN CHASE NA | G6: CHASUS33 | H6: AAA DIRECT LENDING Y LP | I6: 177734 | J6: USD | K6: 2026-06-01 | L6: ACAM-20260601-001 | M6: Wire P1: SF1Y → DL-Y (deficit cover) | N6: B20260601-001
A7: S 17017 | B7: JPMORGAN CHASE NA | C7: CHASUS33 | D7: APOLLO ALIGNED ALTERNATIVES AGR LP | E7: S 23061 | F7: JPMORGAN CHASE NA | G7: CHASUS33 | H7: AAA IDF LP | I7: 60365 | J7: USD | K7: 2026-06-01 | L7: ACAM-20260601-002 | M7: Wire P2: AGG → IDF-AGG (deficit cover) | N7: B20260601-001
A8: S 19834 | B8: JPMORGAN CHASE NA | C8: CHASUS33 | D8: AAA SUB FUND 1-Y LP INV ACC FBO WFG | E8: S 20680 | F8: JPMORGAN CHASE NA | G8: CHASUS33 | H8: AAA SUB FUND 1-YS LP INV FBO WELLS FARGO | I8: 21899 | J8: USD | K8: 2026-06-01 | L8: ACAM-20260601-003 | M8: Wire P3: SF1Y → SF1YS (deficit cover) | N8: B20260601-001
A11: TRADE BOOKING LOADER — CSV Export (6 rows: 2 legs per wire)
A12: Trade Date | B12: Value Date | C12: Fund | D12: Account | E12: Ref Fund | F12: Amount (USD) | G12: CCY | H12: GL Account | I12: Dr/Cr | J12: Cost Centre | K12: Reference | L12: Batch ID
A13: 2026-06-01 | B13: 2026-06-01 | C13: AAA-SF1Y | D13: S 19834 | E13: AAA-DL-Y | F13: -177734 | G13: USD | H13: 1010-CASH | I13: DR | J13: MUM-TREASURY | K13: ACAM-20260601-001 | L13: B20260601-001
A14: 2026-06-01 | B14: 2026-06-01 | C14: AAA-DL-Y | D14: S 20986 | E14: AAA-SF1Y | F14: 177734 | G14: USD | H14: 1010-CASH | I14: CR | J14: MUM-TREASURY | K14: ACAM-20260601-001 | L14: B20260601-001
A15: 2026-06-01 | B15: 2026-06-01 | C15: AAA-AGG | D15: S 17017 | E15: AAA-IDF-AGG | F15: -60365 | G15: USD | H15: 1010-CASH | I15: DR | J15: MUM-TREASURY | K15: ACAM-20260601-002 | L15: B20260601-001
A16: 2026-06-01 | B16: 2026-06-01 | C16: AAA-IDF-AGG | D16: S 23061 | E16: AAA-AGG | F16: 60365 | G16: USD | H16: 1010-CASH | I16: CR | J16: MUM-TREASURY | K16: ACAM-20260601-002 | L16: B20260601-001
A17: 2026-06-01 | B17: 2026-06-01 | C17: AAA-SF1Y | D17: S 19834 | E17: AAA-SF1YS | F17: -21899 | G17: USD | H17: 1010-CASH | I17: DR | J17: MUM-TREASURY | K17: ACAM-20260601-003 | L17: B20260601-001
A18: 2026-06-01 | B18: 2026-06-01 | C18: AAA-SF1YS | D18: S 20680 | E18: AAA-SF1Y | F18: 21899 | G18: USD | H18: 1010-CASH | I18: CR | J18: MUM-TREASURY | K18: ACAM-20260601-003 | L18: B20260601-001
A21: SPOT FX LOADER — XLSX Export (3 conversions)
A22: Fund | B22: Trade Date | C22: Value Date | D22: Sell CCY | E22: Sell Amount | F22: Buy CCY | G22: Buy Amount (USD) | H22: Indicative Rate | I22: Counterparty | J22: Reference | K22: Narrative
A23: AAA-LUX-AGG | B23: 2026-06-01 | C23: 2026-06-03 | D23: EUR | E23: 70000 | F23: USD | G23: 76300 | H23: 1.09 | I23: JP MORGAN FX | J23: ACAM-FX-20260601-001 | K23: Sell excess EUR — LUX-AGG
A24: AAA-MACS-Z | B24: 2026-06-01 | C24: 2026-06-03 | D24: EUR | E24: 240000 | F24: USD | G24: 261600 | H24: 1.09 | I24: JP MORGAN FX | J24: ACAM-FX-20260601-002 | K24: Sell excess EUR — MACS-Z
A25: AAA-HOSTPLUS-II | B25: 2026-06-01 | C25: 2026-06-03 | D25: GBP | E25: 100000 | F25: USD | G25: 127000 | H25: 1.27 | I25: JP MORGAN FX | J25: ACAM-FX-20260601-003 | K25: Sell excess GBP — HOSTPLUS-II

Sheet SETTINGS
A1: ⚙ SETTINGS — ApolloCAM Configuration
A3: 1 · GLOBAL PARAMETERS
A4: PARAMETER | B4: VALUE | C4: DESCRIPTION
A5: AMBER_BUFFER | B5: 1.1 | C5: Multiplier of floor defining the AMBER zone upper boundary
A6: SPOT_VALUE_LAG_DAYS | B6: 2 | C6: Business days to add for spot FX value date (T+N)
A7: FX_STALE_DAYS | B7: 1 | C7: Alert if FX rate is older than this many days
A8: DL_EMAIL | B8: cash_mgmt_dl@apollo.com | C8: Distribution list for daily digest
A9: CONTROLLER_EMAIL | B9: a.shinde@apollo.com | C9: Controller CC on all alerts
A10: DIGEST_ENABLED | B10: TRUE | C10: Enable automated daily digest email
A11: ALERT_ONLY_WHEN_RED | B11: TRUE | C11: Only alert when fund status is RED
A12: MAX_ALERTS_PER_FUND_PER_DAY | B12: 1 | C12: Maximum threshold alerts per fund per day
A13: ADMIN_PASSWORD | B13: ApolloAdmin2026 | C13: Required to unlock Settings and override Loaders
A16: 2 · FUND MASTER (11 Active Funds)
A17: Fund Code | B17: Fund Name | C17: Type | D17: CCY | E17: Floor (USD) | F17: Ceiling (USD) | G17: Routing Source | H17: SSI Account | I17: SSI Bank | J17: SSI BIC | K17: SSI Entity
A18: AAA-AGG | B18: Apollo Aligned Alternatives Aggregator, L.P. | C18: Aggregator | D18: USD | E18: 1500000 | F18: 3000000 | H18: S 17017 | I18: JPMORGAN CHASE NA | J18: CHASUS33 | K18: APOLLO ALIGNED ALTERNATIVES AGR LP
A19: AAA-LUX-AGG | B19: AAA Lux Aggregator, L.P. | C19: Aggregator | D19: USD | E19: 500000 | F19: 1000000 | H19: S 20454 | I19: JPMORGAN CHASE NA | J19: CHASUS33 | K19: AAA LUX AGGREGATOR LP
A20: AAA-IDF-AGG | B20: AAA IDF, L.P. | C20: Aggregator | D20: USD | E20: 150000 | F20: 400000 | G20: AAA-AGG | H20: S 23061 | I20: JPMORGAN CHASE NA | J20: CHASUS33 | K20: AAA IDF LP
A21: AAA-SF1Y | B21: AAA Sub Fund 1-Y, L.P. | C21: Sub-Fund | D21: USD | E21: 2000000 | F21: 5000000 | G21: AAA-AGG | H21: S 19834 | I21: JPMORGAN CHASE NA | J21: CHASUS33 | K21: AAA SUB FUND 1-Y LP INV ACC FBO WFG
A22: AAA-MACS-Z | B22: AAA Multi-Asset Credit Strategies (Z), L.P. | C22: Sub-Fund | D22: USD | E22: 250000 | F22: 650000 | G22: AAA-AGG | H22: S 20510 | I22: JPMORGAN CHASE NA | J22: CHASUS33 | K22: AAA MULTI-ASSET CREDIT STRATEGIES Z LP
A23: AAA-DL-Y | B23: AAA Direct Lending (Y), L.P. | C23: Sub-Fund | D23: USD | E23: 100000 | F23: 300000 | G23: AAA-SF1Y | H23: S 20986 | I23: JPMORGAN CHASE NA | J23: CHASUS33 | K23: AAA DIRECT LENDING Y LP
A24: AAA-HOSTPLUS-II | B24: Apollo HostPlus Credit II Holdings II, L.P. | C24: Sub-Fund | D24: USD | E24: 400000 | F24: 600000 | G24: AAA-AGG | H24: S 22917 | I24: JPMORGAN CHASE NA | J24: CHASUS33 | K24: APOLLO HOSTPLUS CREDIT II HOLDINGS II LP
A25: AAA-SF4Z | B25: AAA Sub Fund 4-Z, L.P. | C25: Sub-Fund | D25: USD | E25: 115000 | F25: 250000 | G25: AAA-AGG | H25: S 19838 | I25: JPMORGAN CHASE NA | J25: CHASUS33 | K25: AAA SUB FUND 4-Z LP INV ACC FBO WFG
A26: AAA-SF2Y | B26: AAA Sub Fund 2-Y, L.P. | C26: Sub-Fund | D26: USD | E26: 110000 | F26: 300000 | G26: AAA-AGG | H26: S 19836 | I26: JPMORGAN CHASE NA | J26: CHASUS33 | K26: AAA SUB FUND 2-Y LP INV ACC FBO WFG
A27: AAA-SF1YS | B27: AAA Sub Fund 1-YS, L.P. | C27: Sub-Fund | D27: USD | E27: 75000 | F27: 200000 | G27: AAA-SF1Y | H27: S 20680 | I27: JPMORGAN CHASE NA | J27: CHASUS33 | K27: AAA SUB FUND 1-YS LP INV FBO WELLS FARGO
A28: AAA-LIBRA | B28: Apollo Libra Credit Opportunities Fund, L.P. | C28: Sub-Fund | D28: USD | E28: 50000 | F28: 120000 | G28: AAA-AGG | H28: S 20404 | I28: JPMORGAN CHASE NA | J28: CHASUS33 | K28: APOLLO LIBRA CREDIT OPPORTUNITIES FUND LP
A30: 3 · SPOT FX THRESHOLDS
A31: Fund Code | B31: Currency | C31: Min Hold (Local) | D31: Auto Propose | E31: FX Counterparty | F31: Settlement Account
A32: AAA-LUX-AGG | B32: EUR | C32: 50000 | D32: YES | E32: JP MORGAN FX | F32: JPEUR-LUXAGG-001
A33: AAA-MACS-Z | B33: EUR | C33: 100000 | D33: YES | E33: JP MORGAN FX | F33: JPEUR-MACSZ-001
A34: AAA-HOSTPLUS-II | B34: GBP | C34: 50000 | D34: YES | E34: JP MORGAN FX | F34: JPGBP-HOSTII-001
A36: 4 · FX RATES (Base → USD)
A37: Base CCY | B37: Quote CCY | C37: Rate | D37: Rate Date
A38: EUR | B38: USD | C38: 1.09 | D38: 2026-06-01
A39: GBP | B39: USD | C39: 1.27 | D39: 2026-06-01
A40: USD | B40: USD | C40: 1 | D40: 2026-06-01

Sheet _DATA
A1: _DATA — Raw Position Import | Do not edit formulas in columns F–G
A2: As-of: 2026-06-01 | Seed: June 2026 | Replace rows 4-50 with new position file daily
A3: Fund Code | B3: Account Name | C3: Report Date | D3: CCY | E3: Local Balance | F3: FX Rate (→USD) | G3: Functional USD
A4: AAA-AGG | B4: Operating USD | C4: 2026-06-01 | D4: USD | E4: 2192987 | F4: 1 | G4: 2192987
A5: AAA-LUX-AGG | B5: Operating USD | C5: 2026-06-01 | D5: USD | E5: 632859 | F5: 1 | G5: 632859
A6: AAA-LUX-AGG | B6: EUR Account | C6: 2026-06-01 | D6: EUR | E6: 120000 | F6: 1.09 | G6: 130800
A7: AAA-IDF-AGG | B7: Operating USD | C7: 2026-06-01 | D7: USD | E7: 89635 | F7: 1 | G7: 89635
A8: AAA-SF1Y | B8: Operating USD | C8: 2026-06-01 | D8: USD | E8: 9281309 | F8: 1 | G8: 9281309
A9: AAA-MACS-Z | B9: Operating USD | C9: 2026-06-01 | D9: USD | E9: 208430 | F9: 1 | G9: 208430
A10: AAA-MACS-Z | B10: EUR Account | C10: 2026-06-01 | D10: EUR | E10: 340000 | F10: 1.09 | G10: 370600
A11: AAA-DL-Y | B11: Operating USD | C11: 2026-06-01 | D11: USD | E11: -77734 | F11: 1 | G11: -77734
A12: AAA-HOSTPLUS-II | B12: Operating USD | C12: 2026-06-01 | D12: USD | E12: 388310 | F12: 1 | G12: 388310
A13: AAA-HOSTPLUS-II | B13: GBP Account | C13: 2026-06-01 | D13: GBP | E13: 150000 | F13: 1.27 | G13: 190500
A14: AAA-SF4Z | B14: Operating USD | C14: 2026-06-01 | D14: USD | E14: 121002 | F14: 1 | G14: 121002
A15: AAA-SF2Y | B15: Operating USD | C15: 2026-06-01 | D15: USD | E15: 114913 | F15: 1 | G15: 114913
... A17: AAA-LIBRA | B17: Operating USD | C17: 2026-06-01 | D17: USD | E17: 131363 | F17: 1 | G17: 131363
F18: =IFERROR(INDEX(SETTINGS!$B$38:$B$40,MATCH(D18,SETTINGS!$A$38:$A$40,0)),1) | G18: =IF(E18="","",E18*F18)
F19: =IFERROR(INDEX(SETTINGS!$B$38:$B$40,MATCH(D19,SETTINGS!$A$38:$A$40,0)),1) | G19: =IF(E19="","",E19*F19)
F20: =IFERROR(INDEX(SETTINGS!$B$38:$B$40,MATCH(D20,SETTINGS!$A$38:$A$40,0)),1) | G20: =IF(E20="","",E20*F20)
F21: =IFERROR(INDEX(SETTINGS!$B$38:$B$40,MATCH(D21,SETTINGS!$A$38:$A$40,0)),1) | G21: =IF(E21="","",E21*F21)
F22: =IFERROR(INDEX(SETTINGS!$B$38:$B$40,MATCH(D22,SETTINGS!$A$38:$A$40,0)),1) | G22: =IF(E22="","",E22*F22)
F23: =IFERROR(INDEX(SETTINGS!$B$38:$B$40,MATCH(D23,SETTINGS!$A$38:$A$40,0)),1) | G23: =IF(E23="","",E23*F23)
F24: =IFERROR(INDEX(SETTINGS!$B$38:$B$40,MATCH(D24,SETTINGS!$A$38:$A$40,0)),1) | G24: =IF(E24="","",E24*F24)
F25: =IFERROR(INDEX(SETTINGS!$B$38:$B$40,MATCH(D25,SETTINGS!$A$38:$A$40,0)),1) | G25: =IF(E25="","",E25*F25)
F26: =IFERROR(INDEX(SETTINGS!$B$38:$B$40,MATCH(D26,SETTINGS!$A$38:$A$40,0)),1) | G26: =IF(E26="","",E26*F26)
F27: =IFERROR(INDEX(SETTINGS!$B$38:$B$40,MATCH(D27,SETTINGS!$A$38:$A$40,0)),1) | G27: =IF(E27="","",E27*F27)
F28: =IFERROR(INDEX(SETTINGS!$B$38:$B$40,MATCH(D28,SETTINGS!$A$38:$A$40,0)),1) | G28: =IF(E28="","",E28*F28)
F29: =IFERROR(INDEX(SETTINGS!$B$38:$B$40,MATCH(D29,SETTINGS!$A$38:$A$40,0)),1) | G29: =IF(E29="","",E29*F29)
... F50: =IFERROR(INDEX(SETTINGS!$B$38:$B$40,MATCH(D50,SETTINGS!$A$38:$A$40,0)),1) | G50: =IF(E50="","",E50*F50)

Sheet _AUDIT
A1: _AUDIT — Immutable Action Log (INSERT ONLY — no edits permitted)
A2: Timestamp | B2: User | C2: Action | D2: Detail
A3: 2026-06-01T08:00:00Z | B3: ashinde | C3: WORKBOOK_OPENED | D3: ApolloCAM.xlsx opened — June 2026 seed data
A4: 2026-06-01T08:01:00Z | B4: ashinde | C4: POSITIONS_LOADED | D4: 14 position rows loaded for run_date 2026-06-01
A5: 2026-06-01T08:02:30Z | B5: ashinde | C5: PROPOSALS_RUN | D5: Wires: 3 | FX: 3 | Batch: B20260601-001
A6: 2026-06-01T08:03:45Z | B6: ashinde | C6: WIRE_APPROVE_ALL | D6: Bulk approved 3 wire proposals
A7: 2026-06-01T08:04:10Z | B7: ashinde | C7: FX_APPROVE_ALL | D7: Bulk approved 3 FX proposals
A8: 2026-06-01T08:05:00Z | B8: ashinde | C8: LOADERS_LOCKED | D8: Loaders sheet locked — Batch B20260601-001
A9: 2026-06-01T08:06:30Z | B9: ashinde | C9: EXPORT_IVP | D9: IVP file exported: IVP_B20260601-001.xlsx (3 rows)
A10: 2026-06-01T08:07:00Z | B10: ashinde | C10: EXPORT_TRADE | D10: Trade file exported: Trade_B20260601-001.csv (6 rows)
A11: 2026-06-01T08:07:30Z | B11: ashinde | C11: EXPORT_SPOT | D11: SpotFX file exported: SpotFX_B20260601-001.xlsx (3 rows)
